ldapie/__init__.py
ldapie/help_context.py
ldapie/help_overlay.py
ldapie/ldapie.py
ldapie/ldapie_utils.py
ldapie/rich_formatter.py
ldapie-0.1.4.dist-info/licenses/LICENSE
ldapie-0.1.4.dist-info/METADATA
ldapie-0.1.4.dist-info/WHEEL
ldapie-0.1.4.dist-info/entry_points.txt
ldapie-0.1.4.dist-info/top_level.txt
ldapie-0.1.4.dist-info/RECORD
