Metadata-Version: 2.4
Name: ldapie
Version: 0.1.4
Summary: A modern LDAP client CLI tool inspired by HTTPie
Home-page: https://github.com/ruslanfialkovskii/ldapie
Author: LDAPie Team
Author-email: LDAPie Team <ruslan.fialkovsky@gmail.com>
License: # GNU GENERAL PUBLIC LICENSE
Requires-Python: >=3.8
License-File: LICENSE
Requires-Dist: ldap3<3.0,>=2.9
Requires-Dist: rich>=12.0.0
Requires-Dist: click>=7.0
Requires-Dist: pydantic>=1.9.0
Requires-Dist: typer>=0.6.0
Requires-Dist: pyyaml>=6.0
Requires-Dist: cryptography>=38.0.0
Requires-Dist: python-dotenv>=0.20.0
Requires-Dist: python-Levenshtein>=0.20.0
Dynamic: author
Dynamic: home-page
Dynamic: license-file
Dynamic: requires-python
